nonebot_plugin_stockhelper/__init__.py
nonebot_plugin_stockhelper-0.1.2.dist-info/METADATA
nonebot_plugin_stockhelper-0.1.2.dist-info/WHEEL
nonebot_plugin_stockhelper-0.1.2.dist-info/RECORD
